LICENSE.txt
README.txt
setup.py
setup_data.py
WhooshDoc.egg-info/PKG-INFO
WhooshDoc.egg-info/SOURCES.txt
WhooshDoc.egg-info/dependency_links.txt
WhooshDoc.egg-info/entry_points.txt
WhooshDoc.egg-info/requires.txt
WhooshDoc.egg-info/top_level.txt
whooshdoc/__init__.py
whooshdoc/app.py
whooshdoc/argcmd.py
whooshdoc/epyhacks.py
whooshdoc/indexem.py
whooshdoc/ipython.py
whooshdoc/search.py
whooshdoc/util.py
whooshdoc/ui/__init__.py
whooshdoc/ui/search.py