Metadata-Version: 1.0
Name: WhooshDoc
Version: 1.0
Summary: Index docstrings for full-text search.
Home-page: http://pypi.python.org/pypi/WhooshDoc
Author: Robert Kern
Author-email: robert.kern@enthought.com
License: UNKNOWN
Platform: UNKNOWN
Classifier: Development Status :: 5 - Production/Stable
Classifier: Environment :: Console
Classifier: Intended Audience :: Developers
Classifier: License :: OSI Approved :: BSD License
Classifier: Operating System :: OS Independent
Classifier: Programming Language :: Python
Classifier: Topic :: Software Development :: Documentation
